tests/__init__.py
tests/test_utils.py
tgym/__init__.py
tgym/core.py
tgym/utils.py
tgym/envs/__init__.py
tgym/envs/trading.py
tgym/gens/__init__.py
tgym/gens/csv.py
tgym/gens/deterministic.py
tgym/gens/random.py
tgym-0.1.1.dist-info/DESCRIPTION.rst
tgym-0.1.1.dist-info/METADATA
tgym-0.1.1.dist-info/RECORD
tgym-0.1.1.dist-info/WHEEL
tgym-0.1.1.dist-info/metadata.json
tgym-0.1.1.dist-info/top_level.txt
